[
  {
    "cards" : [
      26000047,
      28000015,
      27000012,
      26000059,
      26000057,
      26000052,
      26000084,
      28000001
    ],
    "playerName" : "sasiakos",
    "playerTag" : "#2UQJ820UL"
  },
  {
    "cards" : [
      26000045,
      26000006,
      28000008,
      26000032,
      26000106,
      26000102,
      28000012,
      27000004
    ],
    "playerName" : "DW I Cefremanó",
    "playerTag" : "#RL2CGGL"
  },
  {
    "cards" : [
      26000036,
      26000017,
      26000035,
      26000020,
      26000027,
      28000026,
      26000052,
      28000015
    ],
    "playerName" : "Yuri",
    "playerTag" : "#PRU0LP"
  },
  {
    "cards" : [
      26000037,
      26000034,
      26000011,
      28000010,
      26000015,
      26000052,
      28000012,
      28000005
    ],
    "playerName" : "ᴍɪɴᴛᴡʏ",
    "playerTag" : "#2G2L9PRUP"
  },
  {
    "cards" : [
      26000007,
      26000037,
      26000027,
      26000003,
      28000008,
      28000000,
      26000048,
      26000016
    ],
    "playerName" : "törpe",
    "playerTag" : "#2Y9VPCYJ8"
  },
  {
    "cards" : [
      26000045,
      26000002,
      26000011,
      26000021,
      28000012,
      26000030,
      28000011,
      28000003
    ],
    "playerName" : "ベスト | Starboy",
    "playerTag" : "#8U8JR8PV8"
  },
  {
    "cards" : [
      26000014,
      26000045,
      26000059,
      28000003,
      26000068,
      27000009,
      26000041,
      26000084
    ],
    "playerName" : "Shysheep❦︎",
    "playerTag" : "#2LGL8CQG2"
  },
  {
    "cards" : [
      26000056,
      28000015,
      26000050,
      26000040,
      28000026,
      26000053,
      26000058,
      27000004
    ],
    "playerName" : "TBA Robert",
    "playerTag" : "#898R020RR"
  },
  {
    "cards" : [
      26000012,
      26000000,
      28000004,
      26000040,
      28000011,
      26000030,
      27000003,
      26000026
    ],
    "playerName" : "edesanya",
    "playerTag" : "#G98RJG8YV"
  }
]