[
  {
    "cards" : [
      26000004,
      28000000,
      26000042,
      26000046,
      26000036,
      28000008,
      26000062,
      26000050
    ],
    "playerName" : "Last Shadow➰",
    "playerTag" : "#GRR9UURJ8"
  },
  {
    "cards" : [
      26000004,
      26000027,
      26000017,
      28000008,
      28000001,
      26000046,
      26000016,
      26000042
    ],
    "playerName" : "tama",
    "playerTag" : "#V9LV200VU"
  },
  {
    "cards" : [
      26000024,
      28000015,
      26000050,
      26000061,
      26000044,
      26000010,
      28000000,
      26000084
    ],
    "playerName" : "♠️Mugil♠️",
    "playerTag" : "#20L8V9QY9G"
  },
  {
    "cards" : [
      26000056,
      28000015,
      26000058,
      28000000,
      26000053,
      26000050,
      26000040,
      27000004
    ],
    "playerName" : "Johan Cruyff✨",
    "playerTag" : "#PGCYG9U98"
  },
  {
    "cards" : [
      26000015,
      26000000,
      27000012,
      26000034,
      28000015,
      28000007,
      26000085,
      28000012
    ],
    "playerName" : "Aldarkose",
    "playerTag" : "#28CUQL0G"
  },
  {
    "cards" : [
      26000024,
      28000015,
      26000050,
      26000044,
      26000061,
      26000084,
      26000010,
      28000000
    ],
    "playerName" : "Foosa │ 絶対",
    "playerTag" : "#V98PG2QG"
  },
  {
    "cards" : [
      27000002,
      26000000,
      26000056,
      26000023,
      28000015,
      26000054,
      28000000,
      26000041
    ],
    "playerName" : "Cali | 冰晶",
    "playerTag" : "#8J8VVLC"
  },
  {
    "cards" : [
      28000004,
      26000000,
      26000012,
      26000026,
      27000003,
      26000040,
      28000011,
      26000030
    ],
    "playerName" : "Spotu",
    "playerTag" : "#YYG82U8RJ"
  },
  {
    "cards" : [
      26000040,
      26000018,
      27000006,
      26000021,
      28000008,
      26000010,
      26000030,
      26000019
    ],
    "playerName" : "HERMES",
    "playerTag" : "#C0VLVYVLY"
  },
  {
    "cards" : [
      26000008,
      27000009,
      28000008,
      28000024,
      26000029,
      26000087,
      26000057,
      26000032
    ],
    "playerName" : "nUrzijr",
    "playerTag" : "#9JC9Q2VRV"
  },
  {
    "cards" : [
      26000015,
      26000000,
      26000037,
      28000015,
      26000034,
      26000006,
      28000012,
      28000005
    ],
    "playerName" : "Goodweather☃️",
    "playerTag" : "#2J989L9V2"
  },
  {
    "cards" : [
      26000001,
      26000011,
      26000014,
      26000021,
      27000000,
      26000010,
      26000030,
      28000011
    ],
    "playerName" : "I ❤️ M",
    "playerTag" : "#8QUJV9282"
  },
  {
    "cards" : [
      26000030,
      26000106,
      26000010,
      28000002,
      28000006,
      27000007,
      28000011,
      28000005
    ],
    "playerName" : "Adesea",
    "playerTag" : "#RJYULQQRG"
  },
  {
    "cards" : [
      27000012,
      26000006,
      28000008,
      26000020,
      26000083,
      26000052,
      26000032,
      26000050
    ],
    "playerName" : "Noxen",
    "playerTag" : "#90YCVUJP9"
  },
  {
    "cards" : [
      26000064,
      26000065,
      27000006,
      26000021,
      28000014,
      26000010,
      26000084,
      28000011
    ],
    "playerName" : "Kliros",
    "playerTag" : "#9PUCQURRV"
  },
  {
    "cards" : [
      26000084,
      28000000,
      27000008,
      28000011,
      26000001,
      26000000,
      27000006,
      26000010
    ],
    "playerName" : "❄️Aether❄️えん",
    "playerTag" : "#VPPJPYVJJ"
  },
  {
    "cards" : [
      28000017,
      26000034,
      26000013,
      27000013,
      28000003,
      26000102,
      27000006,
      28000018
    ],
    "playerName" : "Taka❤️BAIT™",
    "playerTag" : "#VPQ8PJCVJ"
  },
  {
    "cards" : [
      27000010,
      27000009,
      26000000,
      28000009,
      28000010,
      26000087,
      26000106,
      28000015
    ],
    "playerName" : "Reece James 24",
    "playerTag" : "#P8GCPRQG9"
  },
  {
    "cards" : [
      27000012,
      26000034,
      26000037,
      28000012,
      26000085,
      28000000,
      28000015,
      26000027
    ],
    "playerName" : "Miko │ 火熱",
    "playerTag" : "#CYYV2U0"
  },
  {
    "cards" : [
      26000056,
      26000002,
      27000002,
      26000054,
      28000000,
      26000005,
      26000053,
      28000015
    ],
    "playerName" : "ГолаяДура",
    "playerTag" : "#9QR8PQU0R"
  },
  {
    "cards" : [
      26000017,
      26000003,
      28000008,
      28000016,
      28000012,
      26000033,
      26000010,
      26000018
    ],
    "playerName" : "⚜️CR❤️kzGAMER⚜️",
    "playerTag" : "#20UQJU9Q"
  },
  {
    "cards" : [
      26000026,
      26000041,
      27000003,
      26000011,
      26000030,
      28000011,
      28000004,
      28000003
    ],
    "playerName" : "Alikhan",
    "playerTag" : "#U99JR28PL"
  },
  {
    "cards" : [
      26000045,
      26000103,
      28000008,
      26000021,
      26000025,
      26000043,
      28000005,
      26000022
    ],
    "playerName" : "ʜᴜɴᴛᴇʀ",
    "playerTag" : "#PYUJRRCYQ"
  },
  {
    "cards" : [
      26000001,
      26000000,
      27000006,
      27000008,
      26000010,
      28000011,
      26000084,
      28000000
    ],
    "playerName" : "Watson",
    "playerTag" : "#U2RJP0RQG"
  },
  {
    "cards" : [
      28000004,
      26000102,
      26000040,
      28000011,
      28000003,
      27000000,
      26000030,
      26000031
    ],
    "playerName" : "NoMercy™",
    "playerTag" : "#PCPYL0CQG"
  },
  {
    "cards" : [
      28000004,
      26000000,
      26000026,
      26000041,
      27000003,
      26000030,
      28000003,
      28000011
    ],
    "playerName" : "r1ckdan❤️墓地",
    "playerTag" : "#QP00LURYJ"
  },
  {
    "cards" : [
      26000059,
      26000000,
      27000012,
      28000015,
      26000047,
      28000000,
      26000057,
      26000052
    ],
    "playerName" : "NovA ┃ KanzleR",
    "playerTag" : "#9020R0YQL"
  },
  {
    "cards" : [
      26000001,
      26000000,
      27000006,
      27000008,
      28000000,
      26000010,
      26000084,
      28000011
    ],
    "playerName" : "Aflapoid❤️",
    "playerTag" : "#28Y0PJ98G"
  },
  {
    "cards" : [
      26000008,
      26000006,
      26000037,
      28000008,
      26000032,
      28000001,
      26000080,
      26000029
    ],
    "playerName" : "あずませれん",
    "playerTag" : "#90PJ089V2"
  },
  {
    "cards" : [
      26000015,
      26000004,
      26000035,
      26000048,
      26000067,
      28000012,
      28000002,
      28000026
    ],
    "playerName" : "001",
    "playerTag" : "#YPV9PRC82"
  },
  {
    "cards" : [
      26000000,
      26000015,
      26000023,
      28000010,
      28000009,
      28000012,
      27000009,
      28000015
    ],
    "playerName" : "Я слава мерлоу",
    "playerTag" : "#9VJ0JU9L"
  },
  {
    "cards" : [
      26000050,
      27000009,
      26000017,
      28000009,
      26000033,
      26000067,
      28000016,
      26000020
    ],
    "playerName" : "Clown每✨",
    "playerTag" : "#RCCRQURY"
  },
  {
    "cards" : [
      28000008,
      26000018,
      26000003,
      26000033,
      28000001,
      28000016,
      26000010,
      28000012
    ],
    "playerName" : "✨❤️Aset❤️✨",
    "playerTag" : "#LYRJ9QVGL"
  },
  {
    "cards" : [
      26000036,
      26000027,
      26000035,
      26000054,
      26000083,
      28000016,
      26000052,
      28000015
    ],
    "playerName" : "haer1n",
    "playerTag" : "#UQ2YULY8U"
  },
  {
    "cards" : [
      26000063,
      26000074,
      26000008,
      26000018,
      28000017,
      28000014,
      27000008,
      26000019
    ],
    "playerName" : "Meganail",
    "playerTag" : "#90RU8GYU"
  },
  {
    "cards" : [
      26000010,
      26000000,
      26000001,
      27000008,
      28000000,
      27000006,
      26000084,
      28000011
    ],
    "playerName" : "☆RoSeS\"remix\"☆)",
    "playerTag" : "#LU2CPU8VR"
  },
  {
    "cards" : [
      26000030,
      28000015,
      26000064,
      26000048,
      28000023,
      26000009,
      27000000,
      26000063
    ],
    "playerName" : "Ttimek",
    "playerTag" : "#QJVJ2G99"
  },
  {
    "cards" : [
      26000058,
      26000062,
      26000049,
      26000032,
      26000031,
      26000010,
      28000011,
      27000004
    ],
    "playerName" : "M1racle",
    "playerTag" : "#JJRYUQQY"
  },
  {
    "cards" : [
      26000050,
      27000004,
      26000056,
      26000097,
      26000058,
      26000053,
      26000040,
      28000000
    ],
    "playerName" : "<c2>OYASSUU™",
    "playerTag" : "#CVJV2QPJG"
  },
  {
    "cards" : [
      26000024,
      28000015,
      26000050,
      28000000,
      26000061,
      26000010,
      26000084,
      26000044
    ],
    "playerName" : "ерасыл",
    "playerTag" : "#2VLR0QCV8"
  },
  {
    "cards" : [
      28000017,
      26000034,
      26000014,
      26000005,
      26000003,
      28000010,
      28000001,
      26000018
    ],
    "playerName" : "OcT | Nurs",
    "playerTag" : "#V8YPRCLQP"
  },
  {
    "cards" : [
      28000017,
      26000018,
      26000014,
      26000003,
      26000034,
      28000001,
      28000010,
      26000048
    ],
    "playerName" : "King Nur",
    "playerTag" : "#9J9Q0CQ08"
  },
  {
    "cards" : [
      28000004,
      26000002,
      26000011,
      26000031,
      28000003,
      26000030,
      26000040,
      26000058
    ],
    "playerName" : "DEMON",
    "playerTag" : "#9Y2UUU2C9"
  },
  {
    "cards" : [
      27000002,
      26000002,
      26000056,
      28000015,
      28000000,
      26000005,
      26000053,
      26000054
    ],
    "playerName" : "☆•Amigo•☆",
    "playerTag" : "#90R0Y080"
  },
  {
    "cards" : [
      26000044,
      26000006,
      28000008,
      26000032,
      26000020,
      26000005,
      26000038,
      26000084
    ],
    "playerName" : "tatami",
    "playerTag" : "#V0VYYV9JL"
  },
  {
    "cards" : [
      26000045,
      26000000,
      27000000,
      26000084,
      28000007,
      28000011,
      26000049,
      26000021
    ],
    "playerName" : "Donk",
    "playerTag" : "#9VJG02Q88"
  },
  {
    "cards" : [
      26000055,
      26000027,
      26000036,
      26000052,
      28000002,
      26000061,
      26000039,
      28000000
    ],
    "playerName" : "Axe",
    "playerTag" : "#V8CP8020Q"
  },
  {
    "cards" : [
      26000012,
      26000069,
      26000045,
      28000002,
      28000001,
      26000048,
      28000023,
      26000067
    ],
    "playerName" : "⚡熊猫-NurDos",
    "playerTag" : "#VG2RC0LVR"
  },
  {
    "cards" : [
      26000059,
      26000034,
      26000047,
      26000052,
      26000032,
      28000015,
      27000000,
      26000083
    ],
    "playerName" : "AMANO",
    "playerTag" : "#CVQ2JLQU"
  },
  {
    "cards" : [
      26000010,
      26000062,
      26000004,
      28000012,
      28000018,
      28000008,
      26000084,
      26000021
    ],
    "playerName" : "YERSEIIT",
    "playerTag" : "#UGYJ9C8GG"
  },
  {
    "cards" : [
      26000064,
      26000061,
      26000011,
      26000021,
      26000056,
      26000041,
      28000018,
      26000012
    ],
    "playerName" : "elnuroff | 不屈",
    "playerTag" : "#UVCRJ8LLY"
  },
  {
    "cards" : [
      26000047,
      26000034,
      26000013,
      28000012,
      28000025,
      26000085,
      27000000,
      28000001
    ],
    "playerName" : "Bekzhxn17",
    "playerTag" : "#9UCJLLLP9"
  },
  {
    "cards" : [
      26000055,
      26000062,
      27000006,
      26000021,
      28000007,
      26000102,
      26000084,
      28000015
    ],
    "playerName" : "Lion Fierce",
    "playerTag" : "#LPYRQQGYQ"
  },
  {
    "cards" : [
      26000045,
      26000002,
      26000011,
      26000030,
      28000003,
      28000012,
      26000021,
      28000011
    ],
    "playerName" : "НазиКотик❤️",
    "playerTag" : "#R88RCRC8J"
  }
]