[
  {
    "cards" : [
      26000037,
      26000027,
      27000012,
      28000012,
      26000085,
      28000007,
      26000013,
      26000083
    ],
    "playerName" : "kiki",
    "playerTag" : "#J0GJJY02P"
  },
  {
    "cards" : [
      26000011,
      26000006,
      27000012,
      28000000,
      26000029,
      26000037,
      26000027,
      28000008
    ],
    "playerName" : "Sintee",
    "playerTag" : "#2CGYV0GQ8"
  },
  {
    "cards" : [
      28000003,
      27000000,
      26000041,
      26000011,
      28000011,
      28000004,
      26000040,
      26000030
    ],
    "playerName" : "Cian 3.0",
    "playerTag" : "#JC8CRR992"
  },
  {
    "cards" : [
      26000014,
      26000006,
      28000008,
      26000032,
      26000020,
      26000038,
      26000005,
      26000084
    ],
    "playerName" : "G❄️AT✨Kun",
    "playerTag" : "#Q22UCU2VR"
  },
  {
    "cards" : [
      27000012,
      26000027,
      26000013,
      26000029,
      26000087,
      28000000,
      26000080,
      28000011
    ],
    "playerName" : "喆喆✨白影",
    "playerTag" : "#GG9UCV208"
  }
]